music_mesa_tables-0.2.3.dist-info/METADATA
music_mesa_tables-0.2.3.dist-info/WHEEL
music_mesa_tables-0.2.3.dist-info/licenses/../LICENSE
music_mesa_tables/__init__.py
music_mesa_tables/__init__.pyi
music_mesa_tables/music_mesa_tables.cpython-313t-darwin.so
music_mesa_tables/py.typed
music_mesa_tables-0.2.3.dist-info/RECORD
