Metadata-Version: 2.4
Name: music-mesa-tables
Version: 0.2.3
Classifier: Development Status :: 4 - Beta
Classifier: Intended Audience :: Science/Research
Classifier: License :: OSI Approved :: GNU Lesser General Public License v2 (LGPLv2)
Classifier: Programming Language :: Python :: 3 :: Only
Classifier: Programming Language :: Rust
Requires-Dist: numpy>=2.0
License-File: ../LICENSE
Summary: MESA tables for post-processing of MUSIC simulations
Author-email: Adrien Morison <adrien.morison@gmail.com>
Maintainer-email: Adrien Morison <adrien.morison@gmail.com>
Requires-Python: >=3.10
Project-URL: homepage, https://github.com/amorison/music_mesa_tables
